CHANGES.txt
LICENCE.txt
README.md
setup.py
pu_in_content/__init__.py
pu_in_content/utils.py
pu_in_content.egg-info/PKG-INFO
pu_in_content.egg-info/SOURCES.txt
pu_in_content.egg-info/dependency_links.txt
pu_in_content.egg-info/entry_points.txt
pu_in_content.egg-info/not-zip-safe
pu_in_content.egg-info/requires.txt
pu_in_content.egg-info/top_level.txt
pu_in_content/static/js/pu_in_content.js
pu_in_content/templates/snippets/addform.html
pu_in_content/templates/snippets/editform.html
pu_in_content/templates/snippets/field.html
pu_in_content/templates/snippets/singlefieldform.html
pu_in_content/views/__init__.py
pu_in_content/views/jsonbase.py