Metadata-Version: 1.1
Name: pu-in-content
Version: 1.0.0
Summary: PythonUnited Intranet Content
Home-page: https://github.com/PythonUnited/pu.intranet.content
Author: PythonUnited
Author-email: info@pythonunited.com
License: beer-ware
Keywords: Django Intranet Content
Platform: UNKNOWN
Classifier: Development Status :: 5 - Production/Stable
Classifier: Framework :: Django
Classifier: Intended Audience :: Developers
Classifier: License :: Freely Distributable
Classifier: Programming Language :: Python
Classifier: Topic :: Internet :: WWW/HTTP :: Site Management
Classifier: Topic :: Software Development :: Libraries :: Application Frameworks
